backtracks/__init__.py
backtracks/backtracks.py
backtracks/bailer-jones_edr3.csv
backtracks/plotting.py
backtracks/utils.py
backtracks-0.6.3.dist-info/LICENSE
backtracks-0.6.3.dist-info/METADATA
backtracks-0.6.3.dist-info/WHEEL
backtracks-0.6.3.dist-info/top_level.txt
backtracks-0.6.3.dist-info/RECORD
