Metadata-Version: 2.2
Name: backtracks
Version: 0.6.3
Summary: Python package to fit relative astrometry with background star motion tracks.
Author-email: William Balmer <wbalmer1@jhu.com>, Gilles Otten <gpplotten@asiaa.sinica.edu.tw>, Tomas Stolker <stolker@strw.leidenuniv.nl>
Project-URL: Homepage, https://github.com/wbalmer/backtracks
Project-URL: Issues, https://github.com/wbalmer/backtracks/issues
Classifier: Programming Language :: Python :: 3
Requires-Python: <3.13,>=3.9
License-File: LICENSE
Requires-Dist: astropy
Requires-Dist: astroquery
Requires-Dist: corner
Requires-Dist: dynesty
Requires-Dist: matplotlib
Requires-Dist: numpy
Requires-Dist: novas
Requires-Dist: novas_de405
Requires-Dist: pandas
Requires-Dist: seaborn
Requires-Dist: schwimmbad
Requires-Dist: scipy
